SingleCycleCPU/memory.v
module data_mem(
    input clk, reset, 
    input [1: 0] MemWrite, 
    input [2: 0] MemRead,
    input [31: 0] address, write_data,

    output reg [31: 0] MemRead_data
);

reg [7: 0] data [127: 0];

always @(*) begin
    case (MemRead[1: 0])
        2'b00:begin
            MemRead_data = 32'b0;
        end
        2'b01:begin
            MemRead_data = {data[address + 3], data[address + 2], data[address + 1], data[address]};
        end
        2'b10:begin
            if(MemRead[2]) MemRead_data = {{16{data[address + 1][7]}}, data[address + 1], data[address]};
            else MemRead_data = {16'b0, data[address + 1], data[address]};
        end
        2'b11:begin
            if(MemRead[2]) MemRead_data = {{24{data[address][7]}}, data[address]};
            else MemRead_data = {24'b0, data[address]};
        end 
        default:begin
            MemRead_data = 32'b0;
        end
    endcase
end

always @(posedge clk) begin
    case (MemWrite)
        2'b01:begin
            data[address + 3] = write_data[31: 24];
            data[address + 2] = write_data[23: 16];
            data[address + 1] = write_data[15: 8];
            data[address] = write_data[7: 0];
        end
        2'b10:begin
            data[address + 1] = write_data[15: 8];
            data[address] = write_data[7: 0];
        end
        2'b11:begin
            data[address] = write_data[7: 0];
        end 
        default: begin
            
        end
    endcase
end
endmodule

module Instr_mem (
    input [31: 0] pc,

    output [31: 0] Instr
);
    reg [31: 0] inst_mem[63: 0];
    initial begin
        $readmemh("codes.txt", inst_mem);
    end
    assign Instr = inst_mem[pc >> 2];
endmodule

SingleCycleCPU/alu.v
module alu(
    input [4:0] ALUcontrols,
    input [31:0] a, b,

    output reg [31: 0] out, 
    output reg BranchCondition
);

always @(*) begin
    BranchCondition = 0;
    out = 32'b0;
    case (ALUcontrols)
        5'b00000: out = a + b;
        5'b00001: out = a - b;
        5'b00010: out = a & b;
        5'b00011: out = a | b;
        5'b00100: out = a ^ b;
        5'b00101: out = a << b;
        5'b00110: out = ($signed(a) < ($signed(b))) ? 32'b1 : 32'b0;
        5'b00111: out = (a < b) ? 32'b1 : 32'b0;
        5'b01000: out = a >> b;
        5'b01001: out = ($signed(a)) >>> b;
        5'b01010: begin 
            out = a + b;
            out[0] = 1'b0;
        end
        5'b01011: BranchCondition = (a == b) ? 1'b1 : 1'b0;
        5'b01100: BranchCondition = (a != b) ? 1'b1 : 1'b0;
        5'b01101: BranchCondition = ($signed(a) < $signed(b)) ? 1'b1 : 1'b0;
        5'b01110: BranchCondition = ($signed(a) >= $signed(b)) ? 1'b1 : 1'b0;
        5'b01111: BranchCondition = (a < b) ? 1'b1: 1'b0;
        5'b10000: BranchCondition = (a >= b) ? 1'b1: 1'b0;
        default: out = 32'b0;
    endcase
end

endmodule

module imm(
    input [31: 0] instr,
    input [2: 0] ImmSrc,

    output reg [31: 0] ImmExtend
);

always @(*) begin
    case (ImmSrc)
        3'b000:begin
            ImmExtend = {{20{instr[31]}}, instr[31:20]};
        end
        3'b001:begin
            ImmExtend = {instr[31:12], 12'b0};
        end
        3'b010:begin
            ImmExtend = {{20{instr[31]}}, instr[31:25], instr[11:7]};
        end
        3'b011:begin
            ImmExtend = {{20{instr[31]}}, instr[7], instr[30:25], instr[11:8], 1'b0};
        end
        3'b100:begin
            ImmExtend = {{12{instr[31]}}, instr[19:12], instr[20], instr[30:21], 1'b0};
        end
        3'b101:begin
            ImmExtend = {{20{instr[31]}}, instr[31:20]};
            ImmExtend[10] = 0;
        end
        3'b111:begin
            ImmExtend = 32'b0;
        end 
        default:begin
            
        end 
    endcase
end
endmodule;

SingleCycleCPU/mux.v
module mux_2(
    input signal,
    input [31: 0] a, b,

    output [31: 0] out
);

assign out = (signal == 0) ? a : b;

endmodule

module mux_3(
    input [1: 0] signal,
    input [31: 0] a, b, c,

    output [31: 0] out
);

assign out = (signal == 2'b00) ? a :
             (signal == 2'b01) ? b : c;


endmodule

SingleCycleCPU/reg_file.v
module reg_file(
    input reset, clk, RegWrite,
    input [4: 0] rs1, rs2, target_reg,
    input [31: 0] RegWrite_data,

    output reg [31: 0] RegRead_data1,
    output reg [31: 0] RegRead_data2
);

    reg [31: 0] regs[31: 0];

    always @(posedge clk) begin
        if(RegWrite && target_reg != 5'h0) regs[target_reg] = RegWrite_data;
    end

    initial begin
        regs[5'd2] = 32'd128;
    end

    always @(*) begin
        if(rs1 == 5'h0)begin
            RegRead_data1 = 32'h0000_0000;
        end else begin
            RegRead_data1 = regs[rs1];
        end
    end

    always @(*) begin
        if(rs2 == 5'h0)begin
            RegRead_data2 = 32'h0000_0000;
        end else begin
            RegRead_data2 = regs[rs2];
        end
    end

endmodule

SingleCycleCPU/id.v
module id(
    input [31: 0] instr,

    output [6: 0] opcode,
    output [2: 0] func3,
    output [6: 0] func7,
    output [4: 0] rd,
    output [4: 0] rs1,
    output [4: 0] rs2
);

    assign  opcode  = instr[6:0];
    assign  rs1 = instr[19:15];
    assign  rs2 = instr[24:20];
    assign  rd  = instr[11:7];
    assign  func3  = instr[14:12];
    assign  func7  = instr[31:25];

endmodule;

SingleCycleCPU/controller.v
module controller(
    input [6: 0] opcode,
    input [2: 0] func3,
    input [6: 0] func7,

    output reg [4: 0] ALUcontrols,
    output reg ALUResult_WB_MemRead_data, rs1Data_EX_PC, 
    output reg [1: 0] rs2Data_EX_imm32_4,
    output reg RegWrite, 
    output reg [1: 0] MemWrite, 
    output reg [2: 0] MemRead,
    output reg [2: 0] ImmSrc,
    output reg [1: 0] BranchNoCondition
);
    // 对于每一种类型定义的指令，给出对应的控制信号。
always @(*) begin
    case (opcode)
        // lui
        7'b0110111:begin
            RegWrite = 1;
            ALUResult_WB_MemRead_data = 0;
            rs1Data_EX_PC = 0;
            rs2Data_EX_imm32_4 = 2'b01;
            MemWrite = 2'b00;
            MemRead = 3'b000;
            ALUcontrols = 5'b00000;
            BranchNoCondition = 2'b00;
            ImmSrc = 3'b001;
        end
        // auipc
        7'b0010111:begin
            RegWrite = 1;
            ALUResult_WB_MemRead_data = 0;
            rs1Data_EX_PC = 1;
            rs2Data_EX_imm32_4 = 2'b01;
            MemWrite = 2'b00;
            MemRead = 3'b000;
            ALUcontrols = 5'b00000;
            BranchNoCondition = 2'b00;
            ImmSrc = 3'b001;
        end
        // jal
        7'b1101111:begin
            RegWrite = 1;
            ALUResult_WB_MemRead_data = 0;
            rs1Data_EX_PC = 1;
            rs2Data_EX_imm32_4 = 2'b11;
            MemWrite = 2'b00;
            MemRead = 3'b000;
            ALUcontrols = 5'b00000;
            BranchNoCondition = 2'b01;
            ImmSrc = 3'b100;
        end
        // jalr
        7'b1100111:begin
            RegWrite = 1;
            ALUResult_WB_MemRead_data = 0;
            rs1Data_EX_PC = 1;
            rs2Data_EX_imm32_4 = 2'b11;
            MemWrite = 2'b00;
            MemRead = 3'b000;
            ALUcontrols = 5'b01010;
            BranchNoCondition = 2'b10;
            ImmSrc = 3'b000;
        end
        // B型指令
        7'b1100011:begin
            RegWrite = 0;
            ALUResult_WB_MemRead_data = 0;
            rs1Data_EX_PC = 0;
            rs2Data_EX_imm32_4 = 2'b00;
            MemWrite = 2'b00;
            MemRead = 3'b000;
            BranchNoCondition = 2'b00;
            ImmSrc = 3'b011;
            case (func3)
                // beq
                3'b000:begin
                    ALUcontrols = 5'b01011;
                end
                // bne
                3'b001:begin
                    ALUcontrols = 5'b01100;
                end
                // blt
                3'b100: begin
                    ALUcontrols = 5'b01101;
                end
                // bge
                3'b101:begin
                    ALUcontrols = 5'b01110;
                end
                // bltu
                3'b110:begin
                    ALUcontrols = 5'b01111;
                end
                // bgeu
                3'b111:begin
                    ALUcontrols = 5'b10000;
                end
                default:begin
                    
                end
            endcase
        end
        // L型指令
        7'b0000011:begin
            RegWrite = 1;
            ALUResult_WB_MemRead_data = 1;
            rs1Data_EX_PC = 0;
            rs2Data_EX_imm32_4 = 2'b01;
            MemWrite = 2'b00;
            MemRead = 3'b000;
            ALUcontrols = 5'b00000;
            BranchNoCondition = 2'b00;
            ImmSrc = 3'b000;
            case (func3)
                // lw
                3'b010:begin
                    MemRead = 3'b001;
                end
                // lh
                3'b001:begin
                    MemRead = 3'b110;
                end
                // lb
                3'b000:begin
                    MemRead = 3'b111;
                end
                // lbu
                3'b100:begin
                    MemRead = 3'b011;
                end
                // lhu
                3'b101:begin
                    MemRead = 3'b010;
                end
                default: begin
                    
                end
            endcase
        end
        // S型指令
        7'b0100011:begin
            RegWrite = 0;
            ALUResult_WB_MemRead_data = 0;
            rs1Data_EX_PC = 0;
            rs2Data_EX_imm32_4 = 2'b01;
            MemWrite = 2'b00;
            MemRead = 3'b000;
            ALUcontrols = 5'b00000;
            BranchNoCondition = 2'b00;
            ImmSrc = 3'b010;
            case (func3)
                // sw
                3'b010:begin
                    MemWrite = 2'b01;
                end
                // sh
                3'b001:begin
                    MemWrite = 2'b10;
                end
                // sb
                3'b000:begin
                    MemWrite = 2'b11;
                end
                default: begin
                    
                end
            endcase
        end
        // I型指令
        7'b0010011:begin
            RegWrite = 1;
            ALUResult_WB_MemRead_data = 0;
            rs1Data_EX_PC = 0;
            rs2Data_EX_imm32_4 = 2'b01;
            MemWrite = 2'b00;
            MemRead = 3'b000;
            BranchNoCondition = 2'b00;

            ImmSrc = 3'b000;
            case (func3)
                // addi
                3'b000:begin
                    ALUcontrols = 5'b00000;
                end
                // slti
                3'b010:begin
                    ALUcontrols = 5'b00110;
                end
                // sltiu
                3'b011:begin
                    ALUcontrols = 5'b00111;
                end
                // xori
                3'b100:begin
                    ALUcontrols = 5'b00100;
                end
                // ori
                3'b110:begin
                    ALUcontrols = 5'b00011;
                end
                // andi
                3'b111:begin
                    ALUcontrols = 5'b00010;
                end
                // slli
                3'b001:begin
                    ALUcontrols = 5'b00101;
                end
                // srli, srai
                3'b101:begin
                    if(func7[5])begin
                        ImmSrc = 3'b101;
                        ALUcontrols = 5'b01001;
                    end
                    else ALUcontrols = 5'b01000;
                end
                default:begin
                    
                end
            endcase
        end
        // R型指令
        7'b0110011:begin
            RegWrite = 1;
            ALUResult_WB_MemRead_data = 0;
            rs1Data_EX_PC = 0;
            rs2Data_EX_imm32_4 = 2'b00;
            MemWrite = 2'b00;
            MemRead = 3'b000;
            BranchNoCondition = 2'b00;
            ImmSrc = 3'b111;
            case (func3)
                // sub, add
                3'b000:begin
                    if(func7[5])begin
                        ALUcontrols = 5'b00001;
                    end else begin
                        ALUcontrols = 5'b00000;
                    end
                end
                // or
                3'b110:begin
                    ALUcontrols = 5'b00011;
                end
                // and
                3'b111:begin
                    ALUcontrols = 5'b00010;
                end
                // xor
                3'b100:begin
                    ALUcontrols = 5'b00100;
                end
                // sll
                3'b001:begin
                    ALUcontrols = 5'b00101;
                end
                // slt
                3'b010:begin
                    ALUcontrols = 5'b00110;
                end
                // sltu
                3'b011:begin
                    ALUcontrols = 5'b00111;
                end
                // srl, sra
                3'b101:begin
                    if(func7[5]) ALUcontrols = 5'b01001;
                    else ALUcontrols = 5'b01000;
                end 
                default: begin
                    
                end
            endcase
        end
        default: begin
            
        end
    endcase
end

endmodule;

SingleCycleCPU/pc.v
module pc(
    input reset, clk,
    input [31: 0] next_pc,
    output reg [31: 0] pc
);
    always @(posedge clk) begin
        if(reset) pc <= 32'h5c;
        else pc <= next_pc;
    end
endmodule

module next_pc(
    input [1: 0] BranchNoCondition,
    input BranchCondition,
    input [31: 0] pc, offset, rs1Data,

    output reg [31: 0] next_pc
);
    always @(*) begin
        if(BranchNoCondition == 2'b01) next_pc = pc + offset;
        else if(BranchNoCondition == 2'b10) next_pc = rs1Data + offset;
        else if(BranchCondition) next_pc = pc + offset;
        else if(pc == 32'h94) next_pc = 32'h94;
        else next_pc = pc + 4;
    end
endmodule

SingleCycleCPU/cpu.v
`timescale 1ns / 1ps

module test_cpu();

    reg clk, reset;
    
    cpu cputest(clk, reset);
    
    initial begin
        clk = 1'b0;
        reset = 1'b0;
        #1 reset = 1'b1;
        #1 reset = 1'b0;
    end

    always begin
        #1 clk = ~clk;
    end

    initial begin
        $dumpfile("waveform.vcd");
        $dumpvars(0, test_cpu);
        #100 $finish;
    end
    
endmodule

module cpu(
    input clk, reset
);
    // Data
    wire [31: 0] Instr;               // Instruction
    wire [31: 0] RegWrite_data;       // Data written into rd
    wire [31: 0] RegRead_data1;       // Data read from rs1
    wire [31: 0] RegRead_data2;       // Data read from rs2
    wire [31: 0] ImmExtend;           // Immediate 32bits
    wire [31: 0] SrcA;                // ALU SrcA
    wire [31: 0] SrcB;                // ALU SrcB
    wire [31: 0] ALUResult;           // ALU Result
    wire [31: 0] MemRead_data;        // Data read from memory
    wire [31: 0] pc;                  // Instruction Addr
    wire [31: 0] next_pc;             // Instruction AddrNext 

    wire [4: 0] rd, rs1, rs2; 
    wire [6: 0] opcode;
    wire [2: 0] func3;
    wire [6: 0] func7;

    // Controller
    wire [4: 0] ALUcontrols;          // Ctrl
    wire ALUResult_WB_MemRead_data;   // 
    wire rs1Data_EX_PC;               // 
    wire [1: 0] rs2Data_EX_imm32_4;   // 
    wire RegWrite;                    // sel write back to reg
    wire [1: 0] MemWrite;             // sel write to memory
    wire [2: 0] MemRead;              // sel read from memory
    wire [2: 0] ImmSrc;               // choose immediate type
    wire [1: 0] BranchNoCondition;    // Jump
    wire BranchCondition;             // Branch

    pc PC(
        .reset(reset),
        .clk(clk),
        .next_pc(next_pc),

        .pc(pc)
    );

    next_pc NEXT_PC(
        .BranchNoCondition(BranchNoCondition),
        .BranchCondition(BranchCondition),
        .pc(pc),
        .offset(ImmExtend),
        .rs1Data(RegRead_data1),

        .next_pc(next_pc)
    );

    controller CONTROLLER(
        .opcode(opcode),
        .func3(func3),
        .func7(func7),

        .ALUcontrols(ALUcontrols),
        .ALUResult_WB_MemRead_data(ALUResult_WB_MemRead_data),
        .rs1Data_EX_PC(rs1Data_EX_PC),
        .rs2Data_EX_imm32_4(rs2Data_EX_imm32_4),
        .RegWrite(RegWrite),
        .MemWrite(MemWrite),
        .MemRead(MemRead),
        .ImmSrc(ImmSrc),
        .BranchNoCondition(BranchNoCondition)
    );

    imm IMM(
        .instr(Instr),
        .ImmSrc(ImmSrc),

        .ImmExtend(ImmExtend)
    );

    id ID(
        .instr(Instr),

        .opcode(opcode),
        .func3(func3),
        .func7(func7),
        .rd(rd),
        .rs1(rs1),
        .rs2(rs2)
    );

    Instr_mem INSTRUCTION_MEM(
        .pc(pc),

        .Instr(Instr)
    );

    reg_file REG_FILE(
        .reset(reset),
        .clk(clk),
        .RegWrite(RegWrite),
        .rs1(rs1),
        .rs2(rs2),
        .target_reg(rd),
        .RegWrite_data(RegWrite_data),

        .RegRead_data1(RegRead_data1),
        .RegRead_data2(RegRead_data2)
    );

    mux_2 MUX_WB(
        .signal(ALUResult_WB_MemRead_data),
        .a(ALUResult),
        .b(MemRead_data),

        .out(RegWrite_data)
    );

    mux_3 MUX_EX_B(
        .signal(rs2Data_EX_imm32_4),
        .a(RegRead_data2),
        .b(ImmExtend),
        .c(32'd4),

        .out(SrcB)
    );

    mux_2 MUX_EX_A(
        .signal(rs1Data_EX_PC),
        .a(RegRead_data1),
        .b(pc),

        .out(SrcA)
    );

    alu ALU(
        .ALUcontrols(ALUcontrols),
        .a(SrcA),
        .b(SrcB),

        .out(ALUResult),
        .BranchCondition(BranchCondition)
    );

    data_mem DATA_MEM(
        .clk(clk),
        .reset(reset),
        .address(ALUResult),
        .write_data(RegRead_data2),
        .MemWrite(MemWrite),
        .MemRead(MemRead),

        .MemRead_data(MemRead_data)
    );
endmodule

SingleCycleCPU/waveform.vcd
$date
	Mon Jun 16 15:09:39 2025
$end
$version
	Icarus Verilog
$end
$timescale
	1ps
$end
$scope module test_cpu $end
$var reg 1 ! clk $end
$var reg 1 " reset $end
$scope module cputest $end
$var wire 1 ! clk $end
$var wire 1 " reset $end
$var wire 2 # rs2Data_EX_imm32_4 [1:0] $end
$var wire 5 $ rs2 [4:0] $end
$var wire 1 % rs1Data_EX_PC $end
$var wire 5 & rs1 [4:0] $end
$var wire 5 ' rd [4:0] $end
$var wire 32 ( pc [31:0] $end
$var wire 7 ) opcode [6:0] $end
$var wire 32 * next_pc [31:0] $end
$var wire 7 + func7 [6:0] $end
$var wire 3 , func3 [2:0] $end
$var wire 32 - SrcB [31:0] $end
$var wire 32 . SrcA [31:0] $end
$var wire 32 / RegWrite_data [31:0] $end
$var wire 1 0 RegWrite $end
$var wire 32 1 RegRead_data2 [31:0] $end
$var wire 32 2 RegRead_data1 [31:0] $end
$var wire 2 3 MemWrite [1:0] $end
$var wire 32 4 MemRead_data [31:0] $end
$var wire 3 5 MemRead [2:0] $end
$var wire 32 6 Instr [31:0] $end
$var wire 3 7 ImmSrc [2:0] $end
$var wire 32 8 ImmExtend [31:0] $end
$var wire 2 9 BranchNoCondition [1:0] $end
$var wire 1 : BranchCondition $end
$var wire 5 ; ALUcontrols [4:0] $end
$var wire 1 < ALUResult_WB_MemRead_data $end
$var wire 32 = ALUResult [31:0] $end
$scope module ALU $end
$var wire 32 > b [31:0] $end
$var wire 32 ? a [31:0] $end
$var wire 5 @ ALUcontrols [4:0] $end
$var reg 1 : BranchCondition $end
$var reg 32 A out [31:0] $end
$upscope $end
$scope module CONTROLLER $end
$var wire 7 B opcode [6:0] $end
$var wire 7 C func7 [6:0] $end
$var wire 3 D func3 [2:0] $end
$var reg 1 < ALUResult_WB_MemRead_data $end
$var reg 5 E ALUcontrols [4:0] $end
$var reg 2 F BranchNoCondition [1:0] $end
$var reg 3 G ImmSrc [2:0] $end
$var reg 3 H MemRead [2:0] $end
$var reg 2 I MemWrite [1:0] $end
$var reg 1 0 RegWrite $end
$var reg 1 % rs1Data_EX_PC $end
$var reg 2 J rs2Data_EX_imm32_4 [1:0] $end
$upscope $end
$scope module DATA_MEM $end
$var wire 3 K MemRead [2:0] $end
$var wire 2 L MemWrite [1:0] $end
$var wire 32 M address [31:0] $end
$var wire 1 ! clk $end
$var wire 1 " reset $end
$var wire 32 N write_data [31:0] $end
$var reg 32 O MemRead_data [31:0] $end
$upscope $end
$scope module ID $end
$var wire 5 P rs2 [4:0] $end
$var wire 5 Q rs1 [4:0] $end
$var wire 5 R rd [4:0] $end
$var wire 7 S opcode [6:0] $end
$var wire 32 T instr [31:0] $end
$var wire 7 U func7 [6:0] $end
$var wire 3 V func3 [2:0] $end
$upscope $end
$scope module IMM $end
$var wire 3 W ImmSrc [2:0] $end
$var wire 32 X instr [31:0] $end
$var reg 32 Y ImmExtend [31:0] $end
$upscope $end
$scope module INSTRUCTION_MEM $end
$var wire 32 Z Instr [31:0] $end
$var wire 32 [ pc [31:0] $end
$upscope $end
$scope module MUX_EX_A $end
$var wire 1 % signal $end
$var wire 32 \ out [31:0] $end
$var wire 32 ] b [31:0] $end
$var wire 32 ^ a [31:0] $end
$upscope $end
$scope module MUX_EX_B $end
$var wire 32 _ b [31:0] $end
$var wire 32 ` c [31:0] $end
$var wire 2 a signal [1:0] $end
$var wire 32 b out [31:0] $end
$var wire 32 c a [31:0] $end
$upscope $end
$scope module MUX_WB $end
$var wire 32 d a [31:0] $end
$var wire 32 e b [31:0] $end
$var wire 1 < signal $end
$var wire 32 f out [31:0] $end
$upscope $end
$scope module NEXT_PC $end
$var wire 1 : BranchCondition $end
$var wire 2 g BranchNoCondition [1:0] $end
$var wire 32 h offset [31:0] $end
$var wire 32 i rs1Data [31:0] $end
$var wire 32 j pc [31:0] $end
$var reg 32 k next_pc [31:0] $end
$upscope $end
$scope module PC $end
$var wire 1 ! clk $end
$var wire 32 l next_pc [31:0] $end
$var wire 1 " reset $end
$var reg 32 m pc [31:0] $end
$upscope $end
$scope module REG_FILE $end
$var wire 1 0 RegWrite $end
$var wire 32 n RegWrite_data [31:0] $end
$var wire 1 ! clk $end
$var wire 1 " reset $end
$var wire 5 o rs1 [4:0] $end
$var wire 5 p rs2 [4:0] $end
$var wire 5 q target_reg [4:0] $end
$var reg 32 r RegRead_data1 [31:0] $end
$var reg 32 s RegRead_data2 [31:0] $end
$upscope $end
$upscope $end
$upscope $end
$enddefinitions $end
$comment Show the parameter values. $end
$dumpall
$end
#0
$dumpvars
bx s
bx r
bx q
bx p
bx o
bx n
bx m
bx l
bx k
bx j
bx i
bx h
bx g
bx f
bx e
bx d
bx c
bx b
bx a
b100 `
bx _
bx ^
bx ]
bx \
bx [
bx Z
bx Y
bx X
bx W
bx V
bx U
bx T
bx S
bx R
bx Q
bx P
bx O
bx N
bx M
bx L
bx K
bx J
bx I
bx H
bx G
bx F
bx E
bx D
bx C
bx B
bx A
bx @
bx ?
bx >
bx =
x<
bx ;
x:
bx 9
bx 8
bx 7
bx 6
bx 5
bx 4
bx 3
bx 2
bx 1
x0
bx /
bx .
bx -
bx ,
bx +
bx *
bx )
bx (
bx '
bx &
x%
bx $
bx #
0"
0!
$end
#1000
b1100000 /
b1100000 f
b1100000 n
b11111111111111111111111111100000 -
b11111111111111111111111111100000 >
b11111111111111111111111111100000 b
b1100000 =
b1100000 A
b1100000 M
b1100000 d
0:
b11111111111111111111111111100000 8
b11111111111111111111111111100000 Y
b11111111111111111111111111100000 _
b11111111111111111111111111100000 h
b0 4
b0 O
b0 e
b10000000 .
b10000000 ?
b10000000 \
b0 1
b0 N
b0 c
b0 s
b10000000 2
b10000000 ^
b10000000 i
b10000000 r
b0 ;
b0 @
b0 E
b0 7
b0 G
b0 W
b0 9
b0 F
b0 g
b0 5
b0 H
b0 K
b0 3
b0 I
b0 L
b1 #
b1 J
b1 a
0%
0<
10
b1111111 +
b1111111 C
b1111111 U
b0 ,
b0 D
b0 V
b10 '
b10 R
b10 q
b0 $
b0 P
b0 p
b10 &
b10 Q
b10 o
b10011 )
b10011 B
b10011 S
b11111110000000010000000100010011 6
b11111110000000010000000100010011 T
b11111110000000010000000100010011 X
b11111110000000010000000100010011 Z
b1100000 *
b1100000 k
b1100000 l
b1011100 (
b1011100 [
b1011100 ]
b1011100 j
b1011100 m
1!
1"
#2000
0!
0"
#3000
b11100 -
b11100 >
b11100 b
bx 1
bx N
bx c
bx s
b1 3
b1 I
b1 L
b10 7
b10 G
b10 W
00
b0 +
b0 C
b0 U
b10 ,
b10 D
b10 V
b11100 '
b11100 R
b11100 q
b1 $
b1 P
b1 p
b100011 )
b100011 B
b100011 S
b11100 8
b11100 Y
b11100 _
b11100 h
b100010010111000100011 6
b100010010111000100011 T
b100010010111000100011 X
b100010010111000100011 Z
b1100100 *
b1100100 k
b1100100 l
b1100000 (
b1100000 [
b1100000 ]
b1100000 j
b1100000 m
b1111100 /
b1111100 f
b1111100 n
b1111100 =
b1111100 A
b1111100 M
b1111100 d
b1100000 .
b1100000 ?
b1100000 \
b1100000 2
b1100000 ^
b1100000 i
b1100000 r
1!
#4000
0!
#5000
b1111000 /
b1111000 f
b1111000 n
b1111000 =
b1111000 A
b1111000 M
b1111000 d
b11000 -
b11000 >
b11000 b
b11000 '
b11000 R
b11000 q
b1000 $
b1000 P
b1000 p
b11000 8
b11000 Y
b11000 _
b11000 h
b100000010010110000100011 6
b100000010010110000100011 T
b100000010010110000100011 X
b100000010010110000100011 Z
b1101000 *
b1101000 k
b1101000 l
b1100100 (
b1100100 [
b1100100 ]
b1100100 j
b1100100 m
1!
#6000
0!
#7000
b10000000 /
b10000000 f
b10000000 n
b10000000 =
b10000000 A
b10000000 M
b10000000 d
b100000 -
b100000 >
b100000 b
b0 1
b0 N
b0 c
b0 s
b0 7
b0 G
b0 W
b0 3
b0 I
b0 L
10
b1 +
b1 C
b1 U
b0 ,
b0 D
b0 V
b1000 '
b1000 R
b1000 q
b0 $
b0 P
b0 p
b10011 )
b10011 B
b10011 S
b100000 8
b100000 Y
b100000 _
b100000 h
b10000000010000010000010011 6
b10000000010000010000010011 T
b10000000010000010000010011 X
b10000000010000010000010011 Z
b1101100 *
b1101100 k
b1101100 l
b1101000 (
b1101000 [
b1101000 ]
b1101000 j
b1101000 m
1!
#8000
0!
#9000
b1 /
b1 f
b1 n
b1 =
b1 A
b1 M
b1 d
b0 .
b0 ?
b0 \
b1 -
b1 >
b1 b
bx 1
bx N
bx c
bx s
b0 2
b0 ^
b0 i
b0 r
b0 +
b0 C
b0 U
b1111 '
b1111 R
b1111 q
b1 $
b1 P
b1 p
b0 &
b0 Q
b0 o
b1 8
b1 Y
b1 _
b1 h
b100000000011110010011 6
b100000000011110010011 T
b100000000011110010011 X
b100000000011110010011 Z
b1110000 *
b1110000 k
b1110000 l
b1101100 (
b1101100 [
b1101100 ]
b1101100 j
b1101100 m
1!
#10000
0!
#11000
b1101100 /
b1101100 f
b1101100 n
b1101100 =
b1101100 A
b1101100 M
b1101100 d
b10000000 .
b10000000 ?
b10000000 \
b11111111111111111111111111101100 -
b11111111111111111111111111101100 >
b11111111111111111111111111101100 b
b1 1
b1 N
b1 c
b1 s
b10000000 2
b10000000 ^
b10000000 i
b10000000 r
b1 3
b1 I
b1 L
b10 7
b10 G
b10 W
00
b1111111 +
b1111111 C
b1111111 U
b10 ,
b10 D
b10 V
b1100 '
b1100 R
b1100 q
b1111 $
b1111 P
b1111 p
b1000 &
b1000 Q
b1000 o
b100011 )
b100011 B
b100011 S
b11111111111111111111111111101100 8
b11111111111111111111111111101100 Y
b11111111111111111111111111101100 _
b11111111111111111111111111101100 h
b11111110111101000010011000100011 6
b11111110111101000010011000100011 T
b11111110111101000010011000100011 X
b11111110111101000010011000100011 Z
b1110100 *
b1110100 k
b1110100 l
b1110000 (
b1110000 [
b1110000 ]
b1110000 j
b1110000 m
1!
#12000
0!
#13000
b1101100 /
b1101100 f
b1101100 n
b1101100 =
b1101100 A
b1101100 M
b1101100 d
b11111111111111111111111111101100 -
b11111111111111111111111111101100 >
b11111111111111111111111111101100 b
bx 1
bx N
bx c
bx s
b0 7
b0 G
b0 W
b0 3
b0 I
b0 L
10
b0 ,
b0 D
b0 V
b1111 '
b1111 R
b1111 q
b1100 $
b1100 P
b1100 p
b10011 )
b10011 B
b10011 S
b11111111111111111111111111101100 8
b11111111111111111111111111101100 Y
b11111111111111111111111111101100 _
b11111111111111111111111111101100 h
b11111110110001000000011110010011 6
b11111110110001000000011110010011 T
b11111110110001000000011110010011 X
b11111110110001000000011110010011 Z
b1111000 *
b1111000 k
b1111000 l
b1110100 (
b1110100 [
b1110100 ]
b1110100 j
b1110100 m
1!
#14000
0!
#15000
b1101100 =
b1101100 A
b1101100 M
b1101100 d
b1101100 .
b1101100 ?
b1101100 \
b0 -
b0 >
b0 b
b0 1
b0 N
b0 c
b0 s
b1101100 2
b1101100 ^
b1101100 i
b1101100 r
b0 +
b0 C
b0 U
b1010 '
b1010 R
b1010 q
b0 $
b0 P
b0 p
b1111 &
b1111 Q
b1111 o
b0 8
b0 Y
b0 _
b0 h
b1111000010100010011 6
b1111000010100010011 T
b1111000010100010011 X
b1111000010100010011 Z
b1111100 *
b1111100 k
b1111100 l
b1111000 (
b1111000 [
b1111000 ]
b1111000 j
b1111000 m
1!
#16000
0!
#17000
b10000000 /
b10000000 f
b10000000 n
b10000000 =
b10000000 A
b10000000 M
b10000000 d
b1111100 .
b1111100 ?
b1111100 \
b100 -
b100 >
b100 b
bx 1
bx N
bx c
bx s
bx 2
bx ^
bx i
bx r
b100 7
b100 G
b100 W
b1 9
b1 F
b1 g
b11 #
b11 J
b11 a
1%
b1111100 +
b1111100 C
b1111100 U
b111 ,
b111 D
b111 V
b1 '
b1 R
b1 q
b101 $
b101 P
b101 p
b11111 &
b11111 Q
b11111 o
b1101111 )
b1101111 B
b1101111 S
b11111111111111111111111110000100 8
b11111111111111111111111110000100 Y
b11111111111111111111111110000100 _
b11111111111111111111111110000100 h
b11111000010111111111000011101111 6
b11111000010111111111000011101111 T
b11111000010111111111000011101111 X
b11111000010111111111000011101111 Z
b0 *
b0 k
b0 l
b1111100 (
b1111100 [
b1111100 ]
b1111100 j
b1111100 m
1!
#18000
0!
#19000
b11111111111111111111111111100000 -
b11111111111111111111111111100000 >
b11111111111111111111111111100000 b
b1000000 /
b1000000 f
b1000000 n
b0 1
b0 N
b0 c
b0 s
b1100000 2
b1100000 ^
b1100000 i
b1100000 r
b0 7
b0 G
b0 W
b0 9
b0 F
b0 g
b1 #
b1 J
b1 a
0%
b1000000 =
b1000000 A
b1000000 M
b1000000 d
b1111111 +
b1111111 C
b1111111 U
b0 ,
b0 D
b0 V
b10 '
b10 R
b10 q
b0 $
b0 P
b0 p
b10 &
b10 Q
b10 o
b10011 )
b10011 B
b10011 S
b11111111111111111111111111100000 8
b11111111111111111111111111100000 Y
b11111111111111111111111111100000 _
b11111111111111111111111111100000 h
b1100000 .
b1100000 ?
b1100000 \
b11111110000000010000000100010011 6
b11111110000000010000000100010011 T
b11111110000000010000000100010011 X
b11111110000000010000000100010011 Z
b100 *
b100 k
b100 l
b0 (
b0 [
b0 ]
b0 j
b0 m
1!
#20000
0!
#21000
b11100 -
b11100 >
b11100 b
b10000000 1
b10000000 N
b10000000 c
b10000000 s
b1 3
b1 I
b1 L
b10 7
b10 G
b10 W
00
b0 +
b0 C
b0 U
b10 ,
b10 D
b10 V
b11100 '
b11100 R
b11100 q
b1000 $
b1000 P
b1000 p
b100011 )
b100011 B
b100011 S
b11100 8
b11100 Y
b11100 _
b11100 h
b100000010010111000100011 6
b100000010010111000100011 T
b100000010010111000100011 X
b100000010010111000100011 Z
b1000 *
b1000 k
b1000 l
b100 (
b100 [
b100 ]
b100 j
b100 m
b1011100 /
b1011100 f
b1011100 n
b1011100 =
b1011100 A
b1011100 M
b1011100 d
b1000000 .
b1000000 ?
b1000000 \
b1000000 2
b1000000 ^
b1000000 i
b1000000 r
1!
#22000
0!
