VerilogExamples/example/alu.v
module alu (
    input  [7:0] opa,
    input  [7:0] opb,
    input  [3:0] opcode,
    input        cin,
    output reg [7:0] result,
    output reg       cout
);
    always @(*) begin
        // 默认值设置，防止综合时出现 latch
        result = 8'b0;
        cout   = 0;

        case (opcode)
            4'b0000: {cout, result} = opa + opb + cin; // 唯一需要设置 cout 的地方

            4'b0001: result = ~opa;
            4'b0010: result = opa | opb;
            4'b0011: result = opa & opb;
            4'b0100: result = {opa[6:0], 1'b0};   // SHL
            4'b0101: result = {1'b0, opa[7:1]};   // SHR
            4'b0110: result = {opa[6:0], opa[7]}; // ROL
            4'b0111: result = {opa[0], opa[7:1]}; // ROR
            4'b1001: cout = (opa > opb);          // CMP，只设置 cout，result 已初始化为 0

            default: begin
                result = 8'b0;
                cout   = 0;
            end
        endcase
    end
endmodule

module alu_with_acc (
    input clk,
    input reset,
    input [7:0] opb,
    input [3:0] opcode,
    input cin,
    output [7:0] result,
    output       cout
);

    reg [7:0] acc;
    wire [7:0] alu_result;

    alu u_alu (
        .opa(acc),
        .opb(opb),
        .opcode(opcode),
        .cin(cin),
        .result(alu_result),
        .cout(cout)   // ✅ 直接输出，无需中间变量
    );

    assign result = alu_result;

    always @(posedge clk or posedge reset) begin
        if (reset)
            acc <= 8'b0;
        else
            acc <= alu_result;
    end
endmodule

VerilogExamples/example/alu_tb.v
`timescale 1ns/1ps

module alu_tb;

    reg clk;
    reg reset;
    reg [7:0] opb;
    reg [3:0] opcode;
    reg cin;
    wire [7:0] result;
    wire cout;

    // 实例化 ALU 顶层模块
    alu_with_acc uut (
        .clk(clk),
        .reset(reset),
        .opb(opb),
        .opcode(opcode),
        .cin(cin),
        .result(result),
        .cout(cout)
    );

    // 时钟生成
    initial begin
        clk = 0;
        forever #5 clk = ~clk; // 100MHz 时钟
    end

    // 主测试过程
    initial begin
        $dumpfile("alu_test.vcd");
        $dumpvars(0, alu_tb);

        // 初始化
        reset = 1;
        cin = 0;
        opb = 8'h00;
        opcode = 4'b0000;
        #20;          // 延长复位时间，覆盖一个时钟边沿
        reset = 0;
        @(posedge clk); // 等待复位后的第一个时钟边沿

        // ========== 第一步：ADD ==========
        opb = 8'h23;
        opcode = 4'b0000; // ADD
        cin = 0;
        @(posedge clk);   // 等待时钟边沿更新 acc
        #1;               // 稍作延迟以观察波形

        // ========== 第二步：ADD again ==========
        opb = 8'h05;
        @(posedge clk);
        #1;

        // ========== 第三步：AND ==========
        opcode = 4'b0011; // AND
        opb = 8'h56;
        @(posedge clk);
        #1;

        // ========== 第四步：ROL ==========
        opcode = 4'b0110; // ROL
        @(posedge clk);
        #1;

        // ========== 第五步：ADD A0 ==========
        opcode = 4'b0000; // ADD
        opb = 8'hA0;
        @(posedge clk);
        #1;

        // ========== 第六步：CMP ==========
        opcode = 4'b1001; // CMP
        opb = 8'h50;
        @(posedge clk);
        #1;

        $finish;
    end
endmodule

VerilogExamples/example/alu_test.vcd
$date
	Sun Apr 13 22:05:13 2025
$end
$version
	Icarus Verilog
$end
$timescale
	1ps
$end
$scope module alu_tb $end
$var wire 8 ! result [7:0] $end
$var wire 1 " cout $end
$var reg 1 # cin $end
$var reg 1 $ clk $end
$var reg 8 % opb [7:0] $end
$var reg 4 & opcode [3:0] $end
$var reg 1 ' reset $end
$scope module uut $end
$var wire 1 # cin $end
$var wire 1 $ clk $end
$var wire 8 ( opb [7:0] $end
$var wire 4 ) opcode [3:0] $end
$var wire 1 ' reset $end
$var wire 8 * result [7:0] $end
$var wire 1 " cout $end
$var wire 8 + alu_result [7:0] $end
$var reg 8 , acc [7:0] $end
$scope module u_alu $end
$var wire 1 # cin $end
$var wire 8 - opa [7:0] $end
$var wire 8 . opb [7:0] $end
$var wire 4 / opcode [3:0] $end
$var reg 1 " cout $end
$var reg 8 0 result [7:0] $end
$upscope $end
$upscope $end
$upscope $end
$enddefinitions $end
$comment Show the parameter values. $end
$dumpall
$end
#0
$dumpvars
b0 0
b0 /
b0 .
b0 -
b0 ,
b0 +
b0 *
b0 )
b0 (
1'
b0 &
b0 %
0$
0#
0"
b0 !
$end
#5000
1$
#10000
0$
#15000
1$
#20000
0$
0'
#25000
b100011 !
b100011 *
b100011 +
b100011 0
b100011 %
b100011 (
b100011 .
1$
#30000
0$
#35000
b1000110 !
b1000110 *
b1000110 +
b1000110 0
b100011 ,
b100011 -
1$
#36000
b101000 !
b101000 *
b101000 +
b101000 0
b101 %
b101 (
b101 .
#40000
0$
#45000
b101101 !
b101101 *
b101101 +
b101101 0
b101000 ,
b101000 -
1$
#46000
b0 !
b0 *
b0 +
b0 0
b1010110 %
b1010110 (
b1010110 .
b11 &
b11 )
b11 /
#50000
0$
#55000
b0 ,
b0 -
1$
#56000
b110 &
b110 )
b110 /
#60000
0$
#65000
1$
#66000
b10100000 !
b10100000 *
b10100000 +
b10100000 0
b10100000 %
b10100000 (
b10100000 .
b0 &
b0 )
b0 /
#70000
0$
#75000
1"
b1000000 !
b1000000 *
b1000000 +
b1000000 0
b10100000 ,
b10100000 -
1$
#76000
1"
b0 !
b0 *
b0 +
b0 0
b1010000 %
b1010000 (
b1010000 .
b1001 &
b1001 )
b1001 /
#80000
0$
#85000
0"
b0 ,
b0 -
1$
